{
  "tools": [
    {
      "branch": "main",
      "browser_download_url": "https://github.com/ReVanced/revanced-cli/releases/download/v4.6.0/revanced-cli-4.6.0-all.jar",
      "content_type": "application/java-archive",
      "label": "cli",
      "name": "revanced-cli-4.6.0-all.jar",
      "repository": "revanced/revanced-cli",
      "size": "50856316",
      "timestamp": "2024-04-01T14:57:08Z",
      "version": "v4.6.0"
    },
    {
      "branch": "main",
      "browser_download_url": "https://github.com/ReVanced/revanced-integrations/releases/download/v1.11.1/revanced-integrations-1.11.1.apk",
      "content_type": "application/vnd.android.package-archive",
      "label": "integrations",
      "name": "revanced-integrations-1.11.1.apk",
      "repository": "revanced/revanced-integrations",
      "size": "267928",
      "timestamp": "2024-07-11T18:54:51Z",
      "version": "v1.11.1"
    },
    {
      "branch": "flutter",
      "browser_download_url": "https://github.com/ReVanced/revanced-manager/releases/download/v1.20.1/revanced-manager-v1.20.1.apk",
      "content_type": "application/vnd.android.package-archive",
      "label": "manager",
      "name": "revanced-manager-v1.20.1.apk",
      "repository": "revanced/revanced-manager",
      "size": "44343053",
      "timestamp": "2024-04-05T02:52:20Z",
      "version": "v1.20.1"
    },
    {
      "branch": "main",
      "browser_download_url": "https://github.com/ReVanced/GmsCore/releases/download/v0.3.1.4.240913/app.revanced.android.gms-240913008-signed.apk",
      "content_type": "application/vnd.android.package-archive",
      "label": "microg",
      "name": "app.revanced.android.gms-240913008-signed.apk",
      "repository": "revanced/GmsCore",
      "size": "39705059",
      "timestamp": "2024-04-05T02:37:12Z",
      "version": "v0.3.1.4.240913"
    },
    {
      "branch": "main",
      "browser_download_url": "https://api.github.com/repos/ReVanced/revanced-patcher/tarball/v19.3.1",
      "content_type": "application/x-gzip",
      "label": "patcher",
      "name": "revanced-patcher-v19.3.1.tar.gz",
      "repository": "revanced/revanced-patcher",
      "size": "0",
      "timestamp": "2024-02-14T00:58:49Z",
      "version": "v19.3.1"
    },
    {
      "branch": "main",
      "browser_download_url": "https://github.com/ReVanced/revanced-patches/releases/download/v4.11.0/revanced-patches-4.11.0.jar",
      "content_type": "application/java-archive",
      "label": "patches_jar",
      "name": "revanced-patches-4.11.0.jar",
      "repository": "revanced/revanced-patches",
      "size": "3030064",
      "timestamp": "2024-07-11T18:57:53Z",
      "version": "v4.11.0"
    },
    {
      "branch": "main",
      "browser_download_url": "https://github.com/ReVanced/revanced-patches/releases/download/v4.11.0/patches.json",
      "content_type": "application/json",
      "label": "patches_json",
      "name": "patches.json",
      "repository": "revanced/revanced-patches",
      "size": "76827",
      "timestamp": "2024-07-11T18:57:52Z",
      "version": "v4.11.0"
    }
  ]
}
